hslog/__init__.py
hslog/exceptions.py
hslog/export.py
hslog/filter.py
hslog/packets.py
hslog/parser.py
hslog/player.py
hslog/tokens.py
hslog/utils.py
hslog-1.18.0.dist-info/LICENSE
hslog-1.18.0.dist-info/METADATA
hslog-1.18.0.dist-info/WHEEL
hslog-1.18.0.dist-info/top_level.txt
hslog-1.18.0.dist-info/RECORD
