Metadata-Version: 2.1
Name: hslog
Version: 1.18.0
Summary: Hearthstone Power.log parser
Home-page: https://github.com/HearthSim/python-hslog/
Author: Jerome Leclanche
Author-email: jerome@leclan.ch
License: UNKNOWN
Download-URL: https://github.com/HearthSim/python-hslog/tarball/master
Platform: UNKNOWN
Classifier: Development Status :: 5 - Production/Stable
Classifier: Intended Audience :: Developers
Classifier: License :: OSI Approved :: MIT License
Classifier: Programming Language :: Python
Classifier: Programming Language :: Python :: 3
Classifier: Programming Language :: Python :: 3.6
Classifier: Topic :: Games/Entertainment
License-File: LICENSE
Requires-Dist: aniso8601
Requires-Dist: hearthstone
